fastlz.cp39-win_amd64.pyd
pyfastlz-0.0.1.dist-info/METADATA
pyfastlz-0.0.1.dist-info/WHEEL
pyfastlz-0.0.1.dist-info/top_level.txt
pyfastlz-0.0.1.dist-info/RECORD
